{
  "timestamp": "2025-07-24T21:39:20.312Z",
  "nodeVersion": "v22.17.1",
  "summary": {
    "totalFiles": 9,
    "totalSize": 603061,
    "totalSizeFormatted": "588.9 KB",
    "totalGzippedSize": 422140
  },
  "byType": {
    "js": {
      "count": 7,
      "size": 504714,
      "sizeFormatted": "492.9 KB",
      "percentage": "83.7",
      "gzippedSize": 353298,
      "gzippedSizeFormatted": "345 KB"
    },
    "css": {
      "count": 1,
      "size": 96312,
      "sizeFormatted": "94.1 KB",
      "percentage": "16.0",
      "gzippedSize": 67418,
      "gzippedSizeFormatted": "65.8 KB"
    },
    "html": {
      "count": 1,
      "size": 2035,
      "sizeFormatted": "2 KB",
      "percentage": "0.3",
      "gzippedSize": 1424,
      "gzippedSizeFormatted": "1.4 KB"
    },
    "assets": {
      "count": 0,
      "size": 0,
      "sizeFormatted": "0 B",
      "percentage": "0.0",
      "gzippedSize": 0,
      "gzippedSizeFormatted": "0 B"
    }
  },
  "largestFiles": [
    {
      "name": "index-B2BHAmc5.js",
      "path": "assets\\index-B2BHAmc5.js",
      "size": 209170,
      "sizeFormatted": "204.3 KB",
      "extension": ".js",
      "type": "js",
      "hash": null,
      "gzippedSize": 146419,
      "gzippedSizeFormatted": "143 KB"
    },
    {
      "name": "vendor-v6ZOr5pf.js",
      "path": "js\\vendor-v6ZOr5pf.js",
      "size": 139869,
      "sizeFormatted": "136.6 KB",
      "extension": ".js",
      "type": "js",
      "hash": null,
      "gzippedSize": 97908,
      "gzippedSizeFormatted": "95.6 KB"
    },
    {
      "name": "ui-DFMYqQYr.js",
      "path": "js\\ui-DFMYqQYr.js",
      "size": 97176,
      "sizeFormatted": "94.9 KB",
      "extension": ".js",
      "type": "js",
      "hash": null,
      "gzippedSize": 68023,
      "gzippedSizeFormatted": "66.4 KB"
    },
    {
      "name": "index-1y8MiIWZ.css",
      "path": "css\\index-1y8MiIWZ.css",
      "size": 96312,
      "sizeFormatted": "94.1 KB",
      "extension": ".css",
      "type": "css",
      "hash": null,
      "gzippedSize": 67418,
      "gzippedSizeFormatted": "65.8 KB"
    },
    {
      "name": "query-Cp3n7B2P.js",
      "path": "js\\query-Cp3n7B2P.js",
      "size": 33213,
      "sizeFormatted": "32.4 KB",
      "extension": ".js",
      "type": "js",
      "hash": null,
      "gzippedSize": 23249,
      "gzippedSizeFormatted": "22.7 KB"
    },
    {
      "name": "utils-CrFdsnXa.js",
      "path": "js\\utils-CrFdsnXa.js",
      "size": 20715,
      "sizeFormatted": "20.2 KB",
      "extension": ".js",
      "type": "js",
      "hash": null,
      "gzippedSize": 14500,
      "gzippedSizeFormatted": "14.2 KB"
    },
    {
      "name": "routing-DEroQZhq.js",
      "path": "js\\routing-DEroQZhq.js",
      "size": 4541,
      "sizeFormatted": "4.4 KB",
      "extension": ".js",
      "type": "js",
      "hash": null,
      "gzippedSize": 3178,
      "gzippedSizeFormatted": "3.1 KB"
    },
    {
      "name": "index.html",
      "path": "index.html",
      "size": 2035,
      "sizeFormatted": "2 KB",
      "extension": ".html",
      "type": "html",
      "hash": null,
      "gzippedSize": 1424,
      "gzippedSizeFormatted": "1.4 KB"
    },
    {
      "name": "forms-KTNORM9f.js",
      "path": "js\\forms-KTNORM9f.js",
      "size": 30,
      "sizeFormatted": "30 B",
      "extension": ".js",
      "type": "js",
      "hash": null,
      "gzippedSize": 21,
      "gzippedSizeFormatted": "21 B"
    }
  ],
  "jsChunks": [
    {
      "name": "vendor-v6ZOr5pf.js",
      "path": "js\\vendor-v6ZOr5pf.js",
      "size": 139869,
      "sizeFormatted": "136.6 KB",
      "extension": ".js",
      "type": "js",
      "hash": null,
      "gzippedSize": 97908,
      "gzippedSizeFormatted": "95.6 KB"
    }
  ],
  "recommendations": [
    {
      "type": "success",
      "priority": "info",
      "message": "Bundle size is within recommended limits",
      "suggestion": "Continue monitoring bundle size as the application grows"
    }
  ],
  "thresholdChecks": {
    "totalSize": {
      "current": 603061,
      "threshold": 2097152,
      "passed": true,
      "message": "Total bundle size: 588.9 KB (limit: 2 MB)"
    },
    "jsChunks": {
      "current": 209170,
      "threshold": 524288,
      "passed": true,
      "message": "Largest JS chunk: 204.3 KB"
    },
    "cssSize": {
      "current": 96312,
      "threshold": 102400,
      "passed": true,
      "message": "Total CSS size: 94.1 KB"
    }
  }
}